iya/__init__.py
iya/backend.py
iya/cli.py
iya/frontend.py
iyaa-1.1.0.dist-info/METADATA
iyaa-1.1.0.dist-info/WHEEL
iyaa-1.1.0.dist-info/entry_points.txt
iyaa-1.1.0.dist-info/top_level.txt
iyaa-1.1.0.dist-info/RECORD
