Metadata-Version: 2.4
Name: iyaa
Version: 1.1.0
Summary: Professional Project Bootstrap CLI
Author: Piyush Pal
Author-email: piyushpal9532@gmail.com
License: MIT
Keywords: cli project-generator boilerplate
Requires-Python: >=3.7
Requires-Dist: questionary
Dynamic: author
Dynamic: author-email
Dynamic: keywords
Dynamic: license
Dynamic: requires-dist
Dynamic: requires-python
Dynamic: summary
